{"dead":{"9":1,"26":1},"deal":{"4":1,"5":1,"6":1,"7":19,"8":1,"21":1,"22":1,"23":1,"24":19,"25":1},"dear":{"9":1,"16":1,"26":1},"death":{"7":1,"24":1},"debt":{"8":1,"25":1},"decept":{"9":1,"26":1},"decid":{"9":1,"13":1,"19":1,"26":1,"27":1},"decis":{"9":1,"26":1},"decor":{"1":1},"deed":{"6":1,"23":1},"deep":{"8":1,"25":1},"deeper":{"6":1,"23":1},"deepest":{"8":1,"25":1},"defin":{"4":1,"6":1,"9":1,"10":1,"21":1,"23":1,"26":1,"28":1},"definit":{"27":1},"degre":{"4":1,"10":1,"21":1,"28":1},"delay":{"6":1,"23":1},"delet":{"2":1,"9":1,"26":1},"demor":{"12":1},"deni":{"6":1,"7":1,"23":1,"24":1},"denial":{"1":1,"4":11,"5":6,"6":6,"7":1,"9":6,"10":1,"21":1,"22":6,"23":6,"24":1,"26":6,"27":2,"28":1},"denounc":{"12":1},"depend":{"2":1,"4":1,"10":1,"21":1,"28":1},"depth":{"1":1},"describ":{"6":1,"23":1},"descrip":{"6":1,"23":1,"27":6},"deserv":{"9":1,"26":1},"design":{"8":1,"25":1,"27":1},"desir":{"4":1,"5":1,"6":1,"7":1,"8":1,"9":1,"10":1,"12":1,"21":1,"22":1,"23":1,"24":1,"25":1,"26":1,"28":1},"destruc":{"9":1,"26":1},"devast":{"9":1,"26":1},"develop":{"1":1,"27":1},"devic":{"7":1,"24":1},"devious":{"13":1,"19":1}}